mispr/__init__.py
mispr/common/__init__.py
mispr/common/pubchem.py
mispr/gaussian/__init__.py
mispr/gaussian/database.py
mispr/gaussian/defaults.py
mispr/gaussian/data/h_pot.bib
mispr/gaussian/data/li_pot.bib
mispr/gaussian/data/mg_pot.bib
mispr/gaussian/firetasks/__init__.py
mispr/gaussian/firetasks/geo_transformation.py
mispr/gaussian/firetasks/parse_outputs.py
mispr/gaussian/firetasks/run_calc.py
mispr/gaussian/firetasks/write_inputs.py
mispr/gaussian/fireworks/__init__.py
mispr/gaussian/fireworks/break_mol.py
mispr/gaussian/fireworks/core.py
mispr/gaussian/utilities/__init__.py
mispr/gaussian/utilities/db_utilities.py
mispr/gaussian/utilities/dbdoc.py
mispr/gaussian/utilities/files.py
mispr/gaussian/utilities/fw_utilities.py
mispr/gaussian/utilities/gout.py
mispr/gaussian/utilities/inputs.py
mispr/gaussian/utilities/metadata.py
mispr/gaussian/utilities/misc.py
mispr/gaussian/utilities/mol.py
mispr/gaussian/utilities/rdkit.py
mispr/gaussian/workflows/__init__.py
mispr/gaussian/workflows/base/__init__.py
mispr/gaussian/workflows/base/bde.py
mispr/gaussian/workflows/base/binding_energy.py
mispr/gaussian/workflows/base/core.py
mispr/gaussian/workflows/base/esp.py
mispr/gaussian/workflows/base/ip_ea.py
mispr/gaussian/workflows/base/nmr.py
mispr/hybrid/__init__.py
mispr/hybrid/defaults.py
mispr/hybrid/firetasks/__init__.py
mispr/hybrid/firetasks/nmr_from_md.py
mispr/hybrid/workflows/__init__.py
mispr/hybrid/workflows/core.py
mispr/hybrid/workflows/nmr.py
mispr/lammps/__init__.py
mispr/lammps/database.py
mispr/lammps/defaults.py
mispr/lammps/data/masses.json
mispr/lammps/firetasks/__init__.py
mispr/lammps/firetasks/parse_outputs.py
mispr/lammps/firetasks/run.py
mispr/lammps/firetasks/write_inputs.py
mispr/lammps/fireworks/__init__.py
mispr/lammps/fireworks/core.py
mispr/lammps/tests/__init__.py
mispr/lammps/tests/antechamber.py
mispr/lammps/tests/base_test.py
mispr/lammps/tests/control.py
mispr/lammps/tests/custom_data_workflow.py
mispr/lammps/tests/data.py
mispr-0.0.4.dist-info/LICENSE
mispr-0.0.4.dist-info/METADATA
mispr-0.0.4.dist-info/WHEEL
mispr-0.0.4.dist-info/top_level.txt
mispr-0.0.4.dist-info/RECORD
