Metadata-Version: 2.1
Name: mispr
Version: 0.0.4
Summary: mispr contains FireWorks workflows for Materials Science
Home-page: https://github.com/molmd/mispr
Author: Rasha Atwi, Matthew Bliss
Author-email: rasha.atwi@stonybrook.edu, matthew.bliss@stonybrook.edu
License: UNKNOWN
Platform: UNKNOWN
Classifier: Programming Language :: Python :: 3
Classifier: Development Status :: 3 - Alpha
Classifier: Intended Audience :: Science/Research
Classifier: Intended Audience :: Information Technology
Classifier: Operating System :: OS Independent
Classifier: Topic :: Scientific/Engineering
Requires-Python: >=3.6
License-File: LICENSE
Requires-Dist: numpy (>=1.21.1)
Requires-Dist: pymongo (>=3.11.0)
Requires-Dist: pymongo (<=3.12.0)
Requires-Dist: matplotlib (>=3.3.1)
Requires-Dist: networkx (>=2.5)
Requires-Dist: fireworks (>=1.9.6)
Requires-Dist: monty (>=4.0.0)
Requires-Dist: scipy (>=1.5.2)
Requires-Dist: pandas (>=1.1.2)
Requires-Dist: pubchempy
Requires-Dist: parmed
Requires-Dist: mdproptools
